{
  "name": "record_access2",
  "parameters": [],
  "types": {
    "assets": [],
    "enums": [],
    "records": [
      {
        "name": "my_record2",
        "fields": [
          {
            "name": "x",
            "type": {
              "node": "string",
              "name": null,
              "int_value": null,
              "args": []
            }
          },
          {
            "name": "y",
            "type": {
              "node": "nat",
              "name": null,
              "int_value": null,
              "args": []
            }
          },
          {
            "name": "z",
            "type": {
              "node": "bytes",
              "name": null,
              "int_value": null,
              "args": []
            }
          }
        ],
        "type_michelson": {
          "prim": "pair",
          "int": null,
          "bytes": null,
          "string": null,
          "args": [
            {
              "prim": "string",
              "int": null,
              "bytes": null,
              "string": null,
              "args": [],
              "annots": [
                "%x"
              ],
              "array": [],
              "var_id": null,
              "var_type": null
            },
            {
              "prim": "nat",
              "int": null,
              "bytes": null,
              "string": null,
              "args": [],
              "annots": [
                "%y"
              ],
              "array": [],
              "var_id": null,
              "var_type": null
            },
            {
              "prim": "bytes",
              "int": null,
              "bytes": null,
              "string": null,
              "args": [],
              "annots": [
                "%z"
              ],
              "array": [],
              "var_id": null,
              "var_type": null
            }
          ],
          "annots": [],
          "array": [],
          "var_id": null,
          "var_type": null
        }
      },
      {
        "name": "my_record3",
        "fields": [
          {
            "name": "alpha",
            "type": {
              "node": "string",
              "name": null,
              "int_value": null,
              "args": []
            }
          },
          {
            "name": "beta",
            "type": {
              "node": "nat",
              "name": null,
              "int_value": null,
              "args": []
            }
          }
        ],
        "type_michelson": {
          "prim": "pair",
          "int": null,
          "bytes": null,
          "string": null,
          "args": [
            {
              "prim": "string",
              "int": null,
              "bytes": null,
              "string": null,
              "args": [],
              "annots": [
                "%alpha"
              ],
              "array": [],
              "var_id": null,
              "var_type": null
            },
            {
              "prim": "nat",
              "int": null,
              "bytes": null,
              "string": null,
              "args": [],
              "annots": [
                "%beta"
              ],
              "array": [],
              "var_id": null,
              "var_type": null
            }
          ],
          "annots": [],
          "array": [],
          "var_id": null,
          "var_type": null
        }
      },
      {
        "name": "my_record",
        "fields": [
          {
            "name": "a",
            "type": {
              "node": "record",
              "name": "my_record3",
              "int_value": null,
              "args": []
            }
          },
          {
            "name": "b",
            "type": {
              "node": "record",
              "name": "my_record3",
              "int_value": null,
              "args": []
            }
          },
          {
            "name": "c",
            "type": {
              "node": "bytes",
              "name": null,
              "int_value": null,
              "args": []
            }
          },
          {
            "name": "d",
            "type": {
              "node": "int",
              "name": null,
              "int_value": null,
              "args": []
            }
          },
          {
            "name": "e",
            "type": {
              "node": "string",
              "name": null,
              "int_value": null,
              "args": []
            }
          },
          {
            "name": "f",
            "type": {
              "node": "record",
              "name": "my_record2",
              "int_value": null,
              "args": []
            }
          },
          {
            "name": "g",
            "type": {
              "node": "bytes",
              "name": null,
              "int_value": null,
              "args": []
            }
          },
          {
            "name": "h",
            "type": {
              "node": "record",
              "name": "my_record3",
              "int_value": null,
              "args": []
            }
          }
        ],
        "type_michelson": {
          "prim": "pair",
          "int": null,
          "bytes": null,
          "string": null,
          "args": [
            {
              "prim": "pair",
              "int": null,
              "bytes": null,
              "string": null,
              "args": [
                {
                  "prim": "string",
                  "int": null,
                  "bytes": null,
                  "string": null,
                  "args": [],
                  "annots": [
                    "%alpha"
                  ],
                  "array": [],
                  "var_id": null,
                  "var_type": null
                },
                {
                  "prim": "nat",
                  "int": null,
                  "bytes": null,
                  "string": null,
                  "args": [],
                  "annots": [
                    "%beta"
                  ],
                  "array": [],
                  "var_id": null,
                  "var_type": null
                }
              ],
              "annots": [
                "%a"
              ],
              "array": [],
              "var_id": null,
              "var_type": null
            },
            {
              "prim": "pair",
              "int": null,
              "bytes": null,
              "string": null,
              "args": [
                {
                  "prim": "string",
                  "int": null,
                  "bytes": null,
                  "string": null,
                  "args": [],
                  "annots": [
                    "%alpha"
                  ],
                  "array": [],
                  "var_id": null,
                  "var_type": null
                },
                {
                  "prim": "nat",
                  "int": null,
                  "bytes": null,
                  "string": null,
                  "args": [],
                  "annots": [
                    "%beta"
                  ],
                  "array": [],
                  "var_id": null,
                  "var_type": null
                }
              ],
              "annots": [
                "%b"
              ],
              "array": [],
              "var_id": null,
              "var_type": null
            },
            {
              "prim": "bytes",
              "int": null,
              "bytes": null,
              "string": null,
              "args": [],
              "annots": [
                "%c"
              ],
              "array": [],
              "var_id": null,
              "var_type": null
            },
            {
              "prim": "int",
              "int": null,
              "bytes": null,
              "string": null,
              "args": [],
              "annots": [
                "%d"
              ],
              "array": [],
              "var_id": null,
              "var_type": null
            },
            {
              "prim": "string",
              "int": null,
              "bytes": null,
              "string": null,
              "args": [],
              "annots": [
                "%e"
              ],
              "array": [],
              "var_id": null,
              "var_type": null
            },
            {
              "prim": "pair",
              "int": null,
              "bytes": null,
              "string": null,
              "args": [
                {
                  "prim": "string",
                  "int": null,
                  "bytes": null,
                  "string": null,
                  "args": [],
                  "annots": [
                    "%x"
                  ],
                  "array": [],
                  "var_id": null,
                  "var_type": null
                },
                {
                  "prim": "nat",
                  "int": null,
                  "bytes": null,
                  "string": null,
                  "args": [],
                  "annots": [
                    "%y"
                  ],
                  "array": [],
                  "var_id": null,
                  "var_type": null
                },
                {
                  "prim": "bytes",
                  "int": null,
                  "bytes": null,
                  "string": null,
                  "args": [],
                  "annots": [
                    "%z"
                  ],
                  "array": [],
                  "var_id": null,
                  "var_type": null
                }
              ],
              "annots": [
                "%f"
              ],
              "array": [],
              "var_id": null,
              "var_type": null
            },
            {
              "prim": "bytes",
              "int": null,
              "bytes": null,
              "string": null,
              "args": [],
              "annots": [
                "%g"
              ],
              "array": [],
              "var_id": null,
              "var_type": null
            },
            {
              "prim": "pair",
              "int": null,
              "bytes": null,
              "string": null,
              "args": [
                {
                  "prim": "string",
                  "int": null,
                  "bytes": null,
                  "string": null,
                  "args": [],
                  "annots": [
                    "%alpha"
                  ],
                  "array": [],
                  "var_id": null,
                  "var_type": null
                },
                {
                  "prim": "nat",
                  "int": null,
                  "bytes": null,
                  "string": null,
                  "args": [],
                  "annots": [
                    "%beta"
                  ],
                  "array": [],
                  "var_id": null,
                  "var_type": null
                }
              ],
              "annots": [
                "%h"
              ],
              "array": [],
              "var_id": null,
              "var_type": null
            }
          ],
          "annots": [],
          "array": [],
          "var_id": null,
          "var_type": null
        }
      }
    ],
    "events": []
  },
  "storage": [
    {
      "name": "res_a",
      "type": {
        "node": "record",
        "name": "my_record3",
        "int_value": null,
        "args": []
      },
      "const": false
    },
    {
      "name": "res_b",
      "type": {
        "node": "record",
        "name": "my_record3",
        "int_value": null,
        "args": []
      },
      "const": false
    },
    {
      "name": "res_c",
      "type": {
        "node": "bytes",
        "name": null,
        "int_value": null,
        "args": []
      },
      "const": false
    },
    {
      "name": "res_d",
      "type": {
        "node": "int",
        "name": null,
        "int_value": null,
        "args": []
      },
      "const": false
    },
    {
      "name": "res_e",
      "type": {
        "node": "string",
        "name": null,
        "int_value": null,
        "args": []
      },
      "const": false
    },
    {
      "name": "res_f",
      "type": {
        "node": "record",
        "name": "my_record2",
        "int_value": null,
        "args": []
      },
      "const": false
    },
    {
      "name": "res_g",
      "type": {
        "node": "bytes",
        "name": null,
        "int_value": null,
        "args": []
      },
      "const": false
    },
    {
      "name": "res_h",
      "type": {
        "node": "record",
        "name": "my_record3",
        "int_value": null,
        "args": []
      },
      "const": false
    },
    {
      "name": "res_a_alpha",
      "type": {
        "node": "string",
        "name": null,
        "int_value": null,
        "args": []
      },
      "const": false
    },
    {
      "name": "res_a_beta",
      "type": {
        "node": "nat",
        "name": null,
        "int_value": null,
        "args": []
      },
      "const": false
    },
    {
      "name": "res_b_alpha",
      "type": {
        "node": "string",
        "name": null,
        "int_value": null,
        "args": []
      },
      "const": false
    },
    {
      "name": "res_b_beta",
      "type": {
        "node": "nat",
        "name": null,
        "int_value": null,
        "args": []
      },
      "const": false
    },
    {
      "name": "res_f_x",
      "type": {
        "node": "string",
        "name": null,
        "int_value": null,
        "args": []
      },
      "const": false
    },
    {
      "name": "res_f_y",
      "type": {
        "node": "nat",
        "name": null,
        "int_value": null,
        "args": []
      },
      "const": false
    },
    {
      "name": "res_f_z",
      "type": {
        "node": "bytes",
        "name": null,
        "int_value": null,
        "args": []
      },
      "const": false
    },
    {
      "name": "res_h_alpha",
      "type": {
        "node": "string",
        "name": null,
        "int_value": null,
        "args": []
      },
      "const": false
    },
    {
      "name": "res_h_beta",
      "type": {
        "node": "nat",
        "name": null,
        "int_value": null,
        "args": []
      },
      "const": false
    },
    {
      "name": "r",
      "type": {
        "node": "record",
        "name": "my_record",
        "int_value": null,
        "args": []
      },
      "const": false
    }
  ],
  "storage_type": {
    "value": {
      "prim": "pair",
      "int": null,
      "bytes": null,
      "string": null,
      "args": [
        {
          "prim": "pair",
          "int": null,
          "bytes": null,
          "string": null,
          "args": [
            {
              "prim": "string",
              "int": null,
              "bytes": null,
              "string": null,
              "args": [],
              "annots": [
                "%alpha"
              ],
              "array": [],
              "var_id": null,
              "var_type": null
            },
            {
              "prim": "nat",
              "int": null,
              "bytes": null,
              "string": null,
              "args": [],
              "annots": [
                "%beta"
              ],
              "array": [],
              "var_id": null,
              "var_type": null
            }
          ],
          "annots": [
            "%res_a"
          ],
          "array": [],
          "var_id": null,
          "var_type": null
        },
        {
          "prim": "pair",
          "int": null,
          "bytes": null,
          "string": null,
          "args": [
            {
              "prim": "string",
              "int": null,
              "bytes": null,
              "string": null,
              "args": [],
              "annots": [
                "%alpha"
              ],
              "array": [],
              "var_id": null,
              "var_type": null
            },
            {
              "prim": "nat",
              "int": null,
              "bytes": null,
              "string": null,
              "args": [],
              "annots": [
                "%beta"
              ],
              "array": [],
              "var_id": null,
              "var_type": null
            }
          ],
          "annots": [
            "%res_b"
          ],
          "array": [],
          "var_id": null,
          "var_type": null
        },
        {
          "prim": "bytes",
          "int": null,
          "bytes": null,
          "string": null,
          "args": [],
          "annots": [
            "%res_c"
          ],
          "array": [],
          "var_id": null,
          "var_type": null
        },
        {
          "prim": "int",
          "int": null,
          "bytes": null,
          "string": null,
          "args": [],
          "annots": [
            "%res_d"
          ],
          "array": [],
          "var_id": null,
          "var_type": null
        },
        {
          "prim": "string",
          "int": null,
          "bytes": null,
          "string": null,
          "args": [],
          "annots": [
            "%res_e"
          ],
          "array": [],
          "var_id": null,
          "var_type": null
        },
        {
          "prim": "pair",
          "int": null,
          "bytes": null,
          "string": null,
          "args": [
            {
              "prim": "string",
              "int": null,
              "bytes": null,
              "string": null,
              "args": [],
              "annots": [
                "%x"
              ],
              "array": [],
              "var_id": null,
              "var_type": null
            },
            {
              "prim": "nat",
              "int": null,
              "bytes": null,
              "string": null,
              "args": [],
              "annots": [
                "%y"
              ],
              "array": [],
              "var_id": null,
              "var_type": null
            },
            {
              "prim": "bytes",
              "int": null,
              "bytes": null,
              "string": null,
              "args": [],
              "annots": [
                "%z"
              ],
              "array": [],
              "var_id": null,
              "var_type": null
            }
          ],
          "annots": [
            "%res_f"
          ],
          "array": [],
          "var_id": null,
          "var_type": null
        },
        {
          "prim": "bytes",
          "int": null,
          "bytes": null,
          "string": null,
          "args": [],
          "annots": [
            "%res_g"
          ],
          "array": [],
          "var_id": null,
          "var_type": null
        },
        {
          "prim": "pair",
          "int": null,
          "bytes": null,
          "string": null,
          "args": [
            {
              "prim": "string",
              "int": null,
              "bytes": null,
              "string": null,
              "args": [],
              "annots": [
                "%alpha"
              ],
              "array": [],
              "var_id": null,
              "var_type": null
            },
            {
              "prim": "nat",
              "int": null,
              "bytes": null,
              "string": null,
              "args": [],
              "annots": [
                "%beta"
              ],
              "array": [],
              "var_id": null,
              "var_type": null
            }
          ],
          "annots": [
            "%res_h"
          ],
          "array": [],
          "var_id": null,
          "var_type": null
        },
        {
          "prim": "string",
          "int": null,
          "bytes": null,
          "string": null,
          "args": [],
          "annots": [
            "%res_a_alpha"
          ],
          "array": [],
          "var_id": null,
          "var_type": null
        },
        {
          "prim": "nat",
          "int": null,
          "bytes": null,
          "string": null,
          "args": [],
          "annots": [
            "%res_a_beta"
          ],
          "array": [],
          "var_id": null,
          "var_type": null
        },
        {
          "prim": "string",
          "int": null,
          "bytes": null,
          "string": null,
          "args": [],
          "annots": [
            "%res_b_alpha"
          ],
          "array": [],
          "var_id": null,
          "var_type": null
        },
        {
          "prim": "nat",
          "int": null,
          "bytes": null,
          "string": null,
          "args": [],
          "annots": [
            "%res_b_beta"
          ],
          "array": [],
          "var_id": null,
          "var_type": null
        },
        {
          "prim": "string",
          "int": null,
          "bytes": null,
          "string": null,
          "args": [],
          "annots": [
            "%res_f_x"
          ],
          "array": [],
          "var_id": null,
          "var_type": null
        },
        {
          "prim": "nat",
          "int": null,
          "bytes": null,
          "string": null,
          "args": [],
          "annots": [
            "%res_f_y"
          ],
          "array": [],
          "var_id": null,
          "var_type": null
        },
        {
          "prim": "bytes",
          "int": null,
          "bytes": null,
          "string": null,
          "args": [],
          "annots": [
            "%res_f_z"
          ],
          "array": [],
          "var_id": null,
          "var_type": null
        },
        {
          "prim": "string",
          "int": null,
          "bytes": null,
          "string": null,
          "args": [],
          "annots": [
            "%res_h_alpha"
          ],
          "array": [],
          "var_id": null,
          "var_type": null
        },
        {
          "prim": "nat",
          "int": null,
          "bytes": null,
          "string": null,
          "args": [],
          "annots": [
            "%res_h_beta"
          ],
          "array": [],
          "var_id": null,
          "var_type": null
        },
        {
          "prim": "pair",
          "int": null,
          "bytes": null,
          "string": null,
          "args": [
            {
              "prim": "pair",
              "int": null,
              "bytes": null,
              "string": null,
              "args": [
                {
                  "prim": "string",
                  "int": null,
                  "bytes": null,
                  "string": null,
                  "args": [],
                  "annots": [
                    "%alpha"
                  ],
                  "array": [],
                  "var_id": null,
                  "var_type": null
                },
                {
                  "prim": "nat",
                  "int": null,
                  "bytes": null,
                  "string": null,
                  "args": [],
                  "annots": [
                    "%beta"
                  ],
                  "array": [],
                  "var_id": null,
                  "var_type": null
                }
              ],
              "annots": [
                "%a"
              ],
              "array": [],
              "var_id": null,
              "var_type": null
            },
            {
              "prim": "pair",
              "int": null,
              "bytes": null,
              "string": null,
              "args": [
                {
                  "prim": "string",
                  "int": null,
                  "bytes": null,
                  "string": null,
                  "args": [],
                  "annots": [
                    "%alpha"
                  ],
                  "array": [],
                  "var_id": null,
                  "var_type": null
                },
                {
                  "prim": "nat",
                  "int": null,
                  "bytes": null,
                  "string": null,
                  "args": [],
                  "annots": [
                    "%beta"
                  ],
                  "array": [],
                  "var_id": null,
                  "var_type": null
                }
              ],
              "annots": [
                "%b"
              ],
              "array": [],
              "var_id": null,
              "var_type": null
            },
            {
              "prim": "bytes",
              "int": null,
              "bytes": null,
              "string": null,
              "args": [],
              "annots": [
                "%c"
              ],
              "array": [],
              "var_id": null,
              "var_type": null
            },
            {
              "prim": "int",
              "int": null,
              "bytes": null,
              "string": null,
              "args": [],
              "annots": [
                "%d"
              ],
              "array": [],
              "var_id": null,
              "var_type": null
            },
            {
              "prim": "string",
              "int": null,
              "bytes": null,
              "string": null,
              "args": [],
              "annots": [
                "%e"
              ],
              "array": [],
              "var_id": null,
              "var_type": null
            },
            {
              "prim": "pair",
              "int": null,
              "bytes": null,
              "string": null,
              "args": [
                {
                  "prim": "string",
                  "int": null,
                  "bytes": null,
                  "string": null,
                  "args": [],
                  "annots": [
                    "%x"
                  ],
                  "array": [],
                  "var_id": null,
                  "var_type": null
                },
                {
                  "prim": "nat",
                  "int": null,
                  "bytes": null,
                  "string": null,
                  "args": [],
                  "annots": [
                    "%y"
                  ],
                  "array": [],
                  "var_id": null,
                  "var_type": null
                },
                {
                  "prim": "bytes",
                  "int": null,
                  "bytes": null,
                  "string": null,
                  "args": [],
                  "annots": [
                    "%z"
                  ],
                  "array": [],
                  "var_id": null,
                  "var_type": null
                }
              ],
              "annots": [
                "%f"
              ],
              "array": [],
              "var_id": null,
              "var_type": null
            },
            {
              "prim": "bytes",
              "int": null,
              "bytes": null,
              "string": null,
              "args": [],
              "annots": [
                "%g"
              ],
              "array": [],
              "var_id": null,
              "var_type": null
            },
            {
              "prim": "pair",
              "int": null,
              "bytes": null,
              "string": null,
              "args": [
                {
                  "prim": "string",
                  "int": null,
                  "bytes": null,
                  "string": null,
                  "args": [],
                  "annots": [
                    "%alpha"
                  ],
                  "array": [],
                  "var_id": null,
                  "var_type": null
                },
                {
                  "prim": "nat",
                  "int": null,
                  "bytes": null,
                  "string": null,
                  "args": [],
                  "annots": [
                    "%beta"
                  ],
                  "array": [],
                  "var_id": null,
                  "var_type": null
                }
              ],
              "annots": [
                "%h"
              ],
              "array": [],
              "var_id": null,
              "var_type": null
            }
          ],
          "annots": [
            "%r"
          ],
          "array": [],
          "var_id": null,
          "var_type": null
        }
      ],
      "annots": [],
      "array": [],
      "var_id": null,
      "var_type": null
    },
    "is_storable": true
  },
  "entrypoints": [
    {
      "name": "exec",
      "args": []
    }
  ],
  "getters": [],
  "views": [],
  "errors": []
}